pizza_box/__init__.py
pizza_box/_version.py
pizza_box/tests/__init__.py
pizza_box/tests/conftest.py
pizza_box/tests/test_examples.py
pizza_box-0.0.0.dist-info/AUTHORS.rst
pizza_box-0.0.0.dist-info/LICENSE
pizza_box-0.0.0.dist-info/METADATA
pizza_box-0.0.0.dist-info/WHEEL
pizza_box-0.0.0.dist-info/entry_points.txt
pizza_box-0.0.0.dist-info/top_level.txt
pizza_box-0.0.0.dist-info/RECORD
