Metadata-Version: 2.1
Name: pizza-box
Version: 0.0.0
Summary: Ophyd classes for pizza-box hardware
Home-page: https://github.com/NSLS-II/pizza-box
Author: Brookhaven National Laboratory
Author-email: 
License: BSD-3-Clause
Platform: UNKNOWN
Classifier: Development Status :: 2 - Pre-Alpha
Classifier: Natural Language :: English
Classifier: Programming Language :: Python :: 3
Requires-Python: >=3.7
